{
  "version": 1,
  "isRoot": true,
  "tools": {
    "snitch": {
      "version": "2.0.0",
      "commands": [
        "snitch"
      ]
    },
    "configvalidate": {
      "version": "1.0.0",
      "commands": [
        "config-validate"
      ]
    },
    "dotnet-outdated-tool": {
      "version": "4.6.8",
      "commands": [
        "dotnet-outdated"
      ]
    },
    "dotnet-project-licenses": {
      "version": "2.7.1",
      "commands": [
        "dotnet-project-licenses"
      ]
    },
    "microsoft.sbom.dotnettool": {
      "version": "4.1.4",
      "commands": [
        "sbom-tool"
      ]
    }
  }
}
